LICENSE
MANIFEST.in
README.md
setup.py
bin/makebot
bin/qs_install_examples
qsbot/__init__.py
qsbot/client.py
qsbot.egg-info/PKG-INFO
qsbot.egg-info/SOURCES.txt
qsbot.egg-info/dependency_links.txt
qsbot.egg-info/not-zip-safe
qsbot.egg-info/requires.txt
qsbot.egg-info/top_level.txt
qsbot/basicbot/__init__.py
qsbot/basicbot/parse_command.py
qsbot/examples/01_example.py
qsbot/examples/02_example.py
qsbot/examples/__init__.py