Metadata-Version: 2.1
Name: qsbot
Version: 0.0.1
Summary: A library for easy discord bot development
Home-page: UNKNOWN
Author: Dual-Exhaust
Author-email: kylecsacco@gmail.com
License: MIT
Platform: UNKNOWN
Requires-Python: >=3.7
